lblimg2coords/__init__.py
lblimg2coords/convert.py
lblimg2coords/converter.py
lblimg2coords-0.0.1.dist-info/LICENSE
lblimg2coords-0.0.1.dist-info/METADATA
lblimg2coords-0.0.1.dist-info/WHEEL
lblimg2coords-0.0.1.dist-info/entry_points.txt
lblimg2coords-0.0.1.dist-info/top_level.txt
lblimg2coords-0.0.1.dist-info/RECORD
